loggi/__init__.py
loggi/logger.py
loggi/models.py
loggi/py.typed
loggi-0.5.0.dist-info/METADATA
loggi-0.5.0.dist-info/WHEEL
loggi-0.5.0.dist-info/licenses/LICENSE.txt
loggi-0.5.0.dist-info/RECORD
