Metadata-Version: 2.3
Name: loggi
Version: 0.5.0
Summary: logger boilerplate with dataclass models for parsing
Project-URL: Homepage, https://github.com/matt-manes/loggi
Project-URL: Documentation, https://github.com/matt-manes/loggi/tree/main/docs
Project-URL: Source code, https://github.com/matt-manes/loggi/tree/main/src/loggi
Author-email: Matt Manes <mattmanes@pm.me>
License-File: LICENSE.txt
Keywords: log,logger,logging
Classifier: License :: OSI Approved :: MIT License
Classifier: Operating System :: OS Independent
Classifier: Programming Language :: Python :: 3
Requires-Python: <3.12,>=3.10
Requires-Dist: pathier
Requires-Dist: typing-extensions
Requires-Dist: younotyou
